setup.py
digcomp/__init__.py
digcomp.egg-info/PKG-INFO
digcomp.egg-info/SOURCES.txt
digcomp.egg-info/dependency_links.txt
digcomp.egg-info/top_level.txt